{"is_source_file": true, "format": "Kotlin", "description": "This file defines the HomeFragment class for an Android app, representing the main dashboard UI. It displays activity summaries, weekly progress, and highlights using various UI components and repositories.", "external_files": ["org.example.app.R", "org.example.app.data.ActivityRepository", "org.example.app.data.GoalRepository", "org.example.app.data.WorkoutRepository", "org.example.app.ui.adapters.SimpleCardAdapter", "org.example.app.ui.charts.MiniBarChart"], "external_methods": ["requireContext()", "getString(int)", "getString(int, ...)"], "published": ["HomeFragment"], "classes": [{"name": "HomeFragment", "description": "A Fragment that displays the main dashboard with activity summaries, weekly charts, and quick stats."}], "methods": [{"name": "onCreateView", "description": "Inflates the fragment's layout and initializes UI components."}, {"name": "onResume", "description": "Loads activity data from repositories, updates UI components with today's steps, weekly progress, and highlights."}], "calls": ["inflater.inflate", "findViewById", "requireContext", "actRepo.getTodaySteps", "txtTodaySteps.setText", "actRepo.getLast7DaysSteps", "barChart.setData", "goalRepo.getWeeklyStepsGoal", "progressWeekly.coerceIn", "getString", "workoutRepo.countThisWeek", "actRepo.countActiveDaysThisWeek", "goalRepo.getActiveGoalSummary", "SimpleCardAdapter"], "search-terms": ["HomeFragment", "Dashboard", "Weekly Progress", "Activity Summary", "UI Components", "Android Fragment", "ktx synthetic"], "state": 2, "file_id": 7, "knowledge_revision": 24, "git_revision": "", "hash": "756f12433df9a893c4836eac06554212", "format-version": 4, "code-base-name": "fitness_tracker_frontend", "filename": "fitness_tracker_frontend/app/src/main/kotlin/org/example/app/ui/HomeFragment.kt", "revision_history": [{"24": ""}]}